qiskit_ibm_runtime/VERSION.txt
qiskit_ibm_runtime/__init__.py
qiskit_ibm_runtime/base_primitive.py
qiskit_ibm_runtime/base_runtime_job.py
qiskit_ibm_runtime/batch.py
qiskit_ibm_runtime/constants.py
qiskit_ibm_runtime/estimator.py
qiskit_ibm_runtime/exceptions.py
qiskit_ibm_runtime/hub_group_project.py
qiskit_ibm_runtime/ibm_backend.py
qiskit_ibm_runtime/ibm_qubit_properties.py
qiskit_ibm_runtime/provider_session.py
qiskit_ibm_runtime/qiskit_runtime_service.py
qiskit_ibm_runtime/runtime_job.py
qiskit_ibm_runtime/runtime_job_v2.py
qiskit_ibm_runtime/runtime_options.py
qiskit_ibm_runtime/sampler.py
qiskit_ibm_runtime/session.py
qiskit_ibm_runtime/version.py
qiskit_ibm_runtime/accounts/__init__.py
qiskit_ibm_runtime/accounts/account.py
qiskit_ibm_runtime/accounts/exceptions.py
qiskit_ibm_runtime/accounts/management.py
qiskit_ibm_runtime/accounts/storage.py
qiskit_ibm_runtime/api/__init__.py
qiskit_ibm_runtime/api/auth.py
qiskit_ibm_runtime/api/client_parameters.py
qiskit_ibm_runtime/api/exceptions.py
qiskit_ibm_runtime/api/session.py
qiskit_ibm_runtime/api/clients/__init__.py
qiskit_ibm_runtime/api/clients/auth.py
qiskit_ibm_runtime/api/clients/backend.py
qiskit_ibm_runtime/api/clients/base_websocket_client.py
qiskit_ibm_runtime/api/clients/runtime.py
qiskit_ibm_runtime/api/clients/runtime_ws.py
qiskit_ibm_runtime/api/clients/version.py
qiskit_ibm_runtime/api/rest/__init__.py
qiskit_ibm_runtime/api/rest/base.py
qiskit_ibm_runtime/api/rest/cloud_backend.py
qiskit_ibm_runtime/api/rest/program_job.py
qiskit_ibm_runtime/api/rest/root.py
qiskit_ibm_runtime/api/rest/runtime.py
qiskit_ibm_runtime/api/rest/runtime_session.py
qiskit_ibm_runtime/api/rest/utils/__init__.py
qiskit_ibm_runtime/api/rest/utils/data_mapper.py
qiskit_ibm_runtime/debug_tools/__init__.py
qiskit_ibm_runtime/debug_tools/neat.py
qiskit_ibm_runtime/debug_tools/neat_results.py
qiskit_ibm_runtime/execution_span/__init__.py
qiskit_ibm_runtime/execution_span/double_slice_span.py
qiskit_ibm_runtime-0.33.2.dist-info/LICENSE.txt
qiskit_ibm_runtime-0.33.2.dist-info/METADATA
qiskit_ibm_runtime-0.33.2.dist-info/WHEEL
qiskit_ibm_runtime-0.33.2.dist-info/entry_points.txt
qiskit_ibm_runtime-0.33.2.dist-info/top_level.txt
qiskit_ibm_runtime-0.33.2.dist-info/RECORD
