Metadata-Version: 2.1
Name: qiskit-ibm-runtime
Version: 0.33.2
Summary: IBM Quantum client for Qiskit Runtime.
Home-page: https://github.com/Qiskit/qiskit-ibm-runtime
Author: Qiskit Development Team
Author-email: qiskit@us.ibm.com
License: Apache 2.0
Project-URL: Bug Tracker, https://github.com/Qiskit/qiskit-ibm-runtime/issues
Project-URL: Documentation, https://docs.quantum.ibm.com/
Project-URL: Source Code, https://github.com/Qiskit/qiskit-ibm-runtime
Keywords: qiskit sdk quantum api runtime ibm
Classifier: Environment :: Console
Classifier: License :: OSI Approved :: Apache Software License
Classifier: Intended Audience :: Developers
Classifier: Intended Audience :: Science/Research
Classifier: Operating System :: Microsoft :: Windows
Classifier: Operating System :: MacOS
Classifier: Operating System :: POSIX :: Linux
Classifier: Programming Language :: Python :: 3 :: Only
Classifier: Programming Language :: Python :: 3.8
Classifier: Programming Language :: Python :: 3.9
Classifier: Programming Language :: Python :: 3.10
Classifier: Programming Language :: Python :: 3.11
Classifier: Programming Language :: Python :: 3.12
Classifier: Topic :: Scientific/Engineering
Requires-Python: >=3.8
License-File: LICENSE.txt
Requires-Dist: requests>=2.19
Requires-Dist: requests-ntlm>=1.1.0
Requires-Dist: numpy>=1.13
Requires-Dist: urllib3>=1.21.1
Requires-Dist: python-dateutil>=2.8.0
Requires-Dist: websocket-client>=1.5.1
Requires-Dist: ibm-platform-services>=0.22.6
Requires-Dist: pydantic>=2.5.0
Requires-Dist: qiskit>=1.1.0
Provides-Extra: visualization
Requires-Dist: plotly>=5.23.0; extra == "visualization"
